{"__symbolic":"module","version":1,"metadata":{"document":{"__symbolic":"select","expression":{"__symbolic":"reference","name":"win"},"member":"document"},"location":{"__symbolic":"select","expression":{"__symbolic":"reference","name":"win"},"member":"location"},"gc":{"__symbolic":"error","message":"Expression form not supported","line":16,"character":15},"performance":{"__symbolic":"error","message":"Expression form not supported","line":17,"character":24},"Event":{"__symbolic":"index","expression":{"__symbolic":"reference","name":"win"},"index":"Event"},"MouseEvent":{"__symbolic":"index","expression":{"__symbolic":"reference","name":"win"},"index":"MouseEvent"},"KeyboardEvent":{"__symbolic":"index","expression":{"__symbolic":"reference","name":"win"},"index":"KeyboardEvent"},"EventTarget":{"__symbolic":"index","expression":{"__symbolic":"reference","name":"win"},"index":"EventTarget"},"History":{"__symbolic":"index","expression":{"__symbolic":"reference","name":"win"},"index":"History"},"Location":{"__symbolic":"index","expression":{"__symbolic":"reference","name":"win"},"index":"Location"},"EventListener":{"__symbolic":"index","expression":{"__symbolic":"reference","name":"win"},"index":"EventListener"}}}